servitorconnect/__init__.py
servitorconnect/cli.py
servitorconnect-1.5.0.dist-info/licenses/LICENSE
servitorconnect-1.5.0.dist-info/METADATA
servitorconnect-1.5.0.dist-info/WHEEL
servitorconnect-1.5.0.dist-info/entry_points.txt
servitorconnect-1.5.0.dist-info/top_level.txt
servitorconnect-1.5.0.dist-info/RECORD
