Metadata-Version: 2.4
Name: servitorconnect
Version: 1.5.0
Summary: A tool to repeat intentions hourly from a file or direct input.
Author-email: "AnthroHeart (Thomas Sweet)" <healing@intentionrepeater.com>
License: GPLv3
Project-URL: Homepage, https://github.com/tsweet77/servitorconnect
Classifier: Programming Language :: Python :: 3
Classifier: License :: OSI Approved :: GNU General Public License v3 (GPLv3)
Classifier: Operating System :: OS Independent
Requires-Python: >=3.8
License-File: LICENSE
Dynamic: license-file
